{
  "android": {
    "release": {
      "keystore": "",
      "storePassword": "",
      "alias": "",
      "password": "",
      "keystoreType": ""
    }
  },
  "ios": {
    "release": {
      "keystore": "",
      "storePassword": "",
      "alias": "",
      "password": "",
      "developmentTeam": "XYZ-Company",
      "keystoreType": ""
    },
    "debug": {
      "keystore": "",
      "storePassword": "",
      "alias": "",
      "password": "",
      "developmentTeam": "XYZ-Company",
      "keystoreType": ""
    }
  }
 }
